zakatqr/__init__.py
zakatqr/zakatqr.py
zakatqr-1.2.4.dist-info/LICENSE
zakatqr-1.2.4.dist-info/METADATA
zakatqr-1.2.4.dist-info/WHEEL
zakatqr-1.2.4.dist-info/top_level.txt
zakatqr-1.2.4.dist-info/RECORD
