Metadata-Version: 2.1
Name: zakatqr
Version: 1.2.4
Summary: Django App to Create Zakat Invoice QR Code Image
Home-page: https://github.com/halmogbl/zakat_qr
Author: Hamad
Author-email: hamad.almogbl@gmail.com
Maintainer: Hamad
Maintainer-email: hamad.almogbl@gmail.com
License: MIT
Keywords: django zakat invoice qrcode qr base64 encode
Platform: UNKNOWN
Classifier: Environment :: Web Environment
Classifier: Framework :: Django
Classifier: Intended Audience :: Developers
Classifier: License :: OSI Approved :: MIT License
Classifier: Operating System :: OS Independent
Classifier: Programming Language :: Python :: 3
Classifier: Programming Language :: Python :: 3 :: Only
Classifier: Programming Language :: Python :: 3.5
Classifier: Programming Language :: Python :: 3.6
Classifier: Programming Language :: Python :: 3.7
Classifier: Programming Language :: Python :: 3.8
Classifier: Programming Language :: Python :: 3.9
Classifier: Topic :: Software Development :: Libraries :: Python Modules
License-File: LICENSE
Requires-Dist: uttlv
Requires-Dist: qrcode
